conpyguration/__init__.py
conpyguration/conpy.py
conpyguration/types.py
conpyguration-0.1.0.dist-info/METADATA
conpyguration-0.1.0.dist-info/WHEEL
conpyguration-0.1.0.dist-info/RECORD
