Metadata-Version: 2.3
Name: conpyguration
Version: 0.1.0
Summary: configure your python class
Author: ZeroAct
Author-email: lhj5682@naver.com
Requires-Python: >=3.9,<4.0
Classifier: Programming Language :: Python :: 3
Classifier: Programming Language :: Python :: 3.9
Classifier: Programming Language :: Python :: 3.10
Classifier: Programming Language :: Python :: 3.11
Classifier: Programming Language :: Python :: 3.12
Classifier: Programming Language :: Python :: 3.13
Requires-Dist: docstring-parser (>=0.16,<0.17)
